buffer/__init__.py
buffer/buffer.py
buffer/chunk.py
buffer-0.2.1.dist-info/LICENSE
buffer-0.2.1.dist-info/METADATA
buffer-0.2.1.dist-info/WHEEL
buffer-0.2.1.dist-info/top_level.txt
buffer-0.2.1.dist-info/zip-safe
buffer-0.2.1.dist-info/RECORD
