Metadata-Version: 2.1
Name: buffer
Version: 0.2.1
Summary: A stream buffer backed by a spooled temporary file.
Home-page: https://alexdelorenzo.dev
Author: Alex DeLorenzo
License: AGPL-3.0
Keywords: stream-buffer,stream,buffer,file,buffer,temporary,file
Platform: UNKNOWN
Requires-Python: >=3.6
